{
  "$schema": "https://mintlify.com/docs.json",
  "theme": "mint",
  "name": "AssemblyAI Take-Home",
  "colors": {
    "primary": "#6e5afe"
  },
  "navigation": {
    "groups": [
      {
        "group": "Part 1: iTranslate Demo",
        "pages": ["introduction", "architecture", "pipeline", "edge-cases"]
      },
      {
        "group": "Part 1: Going Further",
        "pages": ["production", "running"]
      },
      {
        "group": "Part 2: Spanglish Inc.",
        "pages": [
          "spanglish/overview",
          "spanglish/fixes",
          "spanglish/scaling",
          "spanglish/privacy"
        ]
      }
    ]
  },
  "appearance": {
    "default": "dark"
  }
}
